OBP_monitoring_v2/__init__.py
OBP_monitoring_v2/asg_elb_healthcheck_required.py
OBP_monitoring_v2/ec2_instance_detailed_monitoring_enabled.py
OBP_monitoring_v2/guard_duty_enabled.py
OBP_monitoring_v2/lambda_concurrency_check.py
OBP_monitoring_v2/lambda_dlq_check.py
OBP_monitoring_v2/rds_enhanced_monitoring_enabled.py
OBP_monitoring_v2/s3_event_notifications_enabled.py
OBP_monitoring_v2/utils.py
OBP_monitoring_v2-0.1.2.dist-info/METADATA
OBP_monitoring_v2-0.1.2.dist-info/WHEEL
OBP_monitoring_v2-0.1.2.dist-info/top_level.txt
OBP_monitoring_v2-0.1.2.dist-info/RECORD
