Metadata-Version: 2.1
Name: OBP-monitoring-v2
Version: 0.1.2
Summary: Provides AWS compliance details
Author-email: "dheeraj.banodha" <dheeraj.banodha@impetus.com>, "ravish.sharma" <ravish.sharma@impetus.com>
Classifier: Programming Language :: Python :: 3
Classifier: Operating System :: OS Independent
Requires-Python: >=3.7
Requires-Dist: boto3
Requires-Dist: pytz
